langchain_google_community/__init__.py
langchain_google_community/_utils.py
langchain_google_community/bigquery.py
langchain_google_community/bigquery_vector_search.py
langchain_google_community/bq_storage_vectorstores/_base.py
langchain_google_community/bq_storage_vectorstores/bigquery.py
langchain_google_community/bq_storage_vectorstores/featurestore.py
langchain_google_community/bq_storage_vectorstores/utils.py
langchain_google_community/docai.py
langchain_google_community/documentai_warehouse.py
langchain_google_community/drive.py
langchain_google_community/gcs_directory.py
langchain_google_community/gcs_file.py
langchain_google_community/gmail/__init__.py
langchain_google_community/gmail/base.py
langchain_google_community/gmail/create_draft.py
langchain_google_community/gmail/get_message.py
langchain_google_community/gmail/get_thread.py
langchain_google_community/gmail/loader.py
langchain_google_community/gmail/search.py
langchain_google_community/gmail/send_message.py
langchain_google_community/gmail/toolkit.py
langchain_google_community/gmail/utils.py
langchain_google_community/google_speech_to_text.py
langchain_google_community/places_api.py
langchain_google_community/search.py
langchain_google_community/texttospeech.py
langchain_google_community/translate.py
langchain_google_community/vertex_ai_search.py
langchain_google_community/vertex_check_grounding.py
langchain_google_community/vertex_rank.py
langchain_google_community/vision.py
gigachain_google_community-2.0.0.dist-info/LICENSE
gigachain_google_community-2.0.0.dist-info/METADATA
gigachain_google_community-2.0.0.dist-info/WHEEL
gigachain_google_community-2.0.0.dist-info/RECORD
