Metadata-Version: 2.1
Name: gigachain-google-community
Version: 2.0.0
Summary: An integration package connecting miscellaneous Google's products and LangChain
Home-page: https://github.com/langchain-ai/langchain-google
License: MIT
Requires-Python: >=3.9,<4.0
Classifier: License :: OSI Approved :: MIT License
Classifier: Programming Language :: Python :: 3
Classifier: Programming Language :: Python :: 3.9
Classifier: Programming Language :: Python :: 3.10
Classifier: Programming Language :: Python :: 3.11
Classifier: Programming Language :: Python :: 3.12
Provides-Extra: bigquery
Provides-Extra: docai
Provides-Extra: drive
Provides-Extra: featurestore
Provides-Extra: gcs
Provides-Extra: gmail
Provides-Extra: places
Provides-Extra: speech
Provides-Extra: texttospeech
Provides-Extra: translate
Provides-Extra: vertexaisearch
Provides-Extra: vision
Requires-Dist: beautifulsoup4 (>=4.12.3,<5.0.0) ; extra == "gmail"
Requires-Dist: db-dtypes (>=1.2.0,<2.0.0) ; extra == "featurestore"
Requires-Dist: gapic-google-longrunning (>=0.11.2,<0.12.0) ; extra == "docai"
Requires-Dist: gigachain-community (>=0.2.16post2)
Requires-Dist: gigachain-core (>=0.2.38post2,<0.4)
Requires-Dist: google-api-core (>=2.17.1,<3.0.0)
Requires-Dist: google-api-python-client (>=2.122.0,<3.0.0)
Requires-Dist: google-auth-httplib2 (>=0.2.0,<0.3.0) ; extra == "drive" or extra == "gmail"
Requires-Dist: google-auth-oauthlib (>=1.2.0,<2.0.0) ; extra == "drive" or extra == "gmail"
Requires-Dist: google-cloud-aiplatform (>=1.56.0,<2.0.0) ; extra == "featurestore"
Requires-Dist: google-cloud-bigquery (>=3.21.0,<4.0.0) ; extra == "bigquery"
Requires-Dist: google-cloud-bigquery-storage (>=2.6.0,<3) ; extra == "featurestore"
Requires-Dist: google-cloud-contentwarehouse (>=0.7.7,<0.8.0) ; extra == "docai"
Requires-Dist: google-cloud-core (>=2.4.1,<3.0.0)
Requires-Dist: google-cloud-discoveryengine (>=0.11.13,<0.12.0) ; extra == "vertexaisearch"
Requires-Dist: google-cloud-documentai (>=2.26.0,<3.0.0) ; extra == "docai"
Requires-Dist: google-cloud-documentai-toolbox (>=0.13.3a0,<0.14.0) ; extra == "docai"
Requires-Dist: google-cloud-speech (>=2.26.0,<3.0.0) ; extra == "speech"
Requires-Dist: google-cloud-storage (>=2.16.0,<3.0.0) ; extra == "gcs"
Requires-Dist: google-cloud-texttospeech (>=2.16.3,<3.0.0) ; extra == "texttospeech"
Requires-Dist: google-cloud-translate (>=3.15.3,<4.0.0) ; extra == "translate"
Requires-Dist: google-cloud-vision (>=3.7.2,<4.0.0) ; extra == "vision"
Requires-Dist: googlemaps (>=4.10.0,<5.0.0) ; extra == "places"
Requires-Dist: grpcio (>=1.62.0,<2.0.0)
Requires-Dist: pandas (>=1.0.0) ; (python_full_version >= "3.8.1" and python_version < "3.12") and (extra == "featurestore")
Requires-Dist: pandas (>=2.0.0,<3.0) ; (python_version >= "3.12" and python_version < "4.0") and (extra == "featurestore")
Requires-Dist: pyarrow (>=6.0.1) ; extra == "featurestore"
Requires-Dist: pydantic (>=2.7.4,<3.0.0) ; extra == "featurestore"
Requires-Dist: tenacity (>=8.3.0,<8.4.0)
Project-URL: Repository, https://github.com/langchain-ai/langchain-google
Project-URL: Source Code, https://github.com/langchain-ai/langchain-google/tree/main/libs/community
